LICENSE.txt
pyproject.toml
setup.py
poonia/__init__.py
poonia/__main__.py
poonia/data.py
poonia/text.py
poonia/utils.py
poonia.egg-info/PKG-INFO
poonia.egg-info/SOURCES.txt
poonia.egg-info/dependency_links.txt
poonia.egg-info/entry_points.txt
poonia.egg-info/requires.txt
poonia.egg-info/top_level.txt
poonia/commands/__init__.py
poonia/commands/epub.py
poonia/commands/ff.py
poonia/commands/fs.py
poonia/commands/io.py
poonia/commands/run.py
poonia/commands/sqexec.py
poonia/commands/tpl.py