Metadata-Version: 2.1
Name: poonia
Version: 0.1.40
Summary: Collection of small utilities
Author: proteus
License:                     GNU AFFERO GENERAL PUBLIC LICENSE
Classifier: License :: OSI Approved :: GNU Affero General Public License v3 or later (AGPLv3+)
Classifier: Programming Language :: Python
Classifier: Development Status :: 4 - Beta
Classifier: Topic :: Utilities
Requires-Python: >=3.8
License-File: LICENSE.txt
Requires-Dist: Click
Requires-Dist: Pillow
Requires-Dist: jinja2
Requires-Dist: importlib-metadata; python_version < "3.10"
